test_timespent/__init__.py
test_timespent/test_timespent.py
timespent/__init__.py
timespent/timespent.py
timespent-1.0.1.dist-info/LICENSE
timespent-1.0.1.dist-info/METADATA
timespent-1.0.1.dist-info/WHEEL
timespent-1.0.1.dist-info/top_level.txt
timespent-1.0.1.dist-info/RECORD
