Metadata-Version: 2.1
Name: timespent
Version: 1.0.1
Summary: Python Package to Calculate time spent for any list of dict-like objects with date/time data
Author-email: Joseph Gonzalez Diaz <jgonzalezdiaz@ebay.com>
Project-URL: Homepage, https://github.com/ebay/timespent
Project-URL: Issues, https://github.com/ebay/timespent/issues
Classifier: Programming Language :: Python :: 3
Classifier: License :: OSI Approved :: Apache Software License
Classifier: Operating System :: OS Independent
Requires-Python: >=3.8
License-File: LICENSE
Requires-Dist: clientwrapper
